LICENSE
MANIFEST.in
README.rst
requirements.txt
requirements_test.txt
setup.py
crypto_price_rss/__init__.py
crypto_price_rss/cli.py
crypto_price_rss.egg-info/PKG-INFO
crypto_price_rss.egg-info/SOURCES.txt
crypto_price_rss.egg-info/dependency_links.txt
crypto_price_rss.egg-info/entry_points.txt
crypto_price_rss.egg-info/requires.txt
crypto_price_rss.egg-info/top_level.txt
crypto_price_rss.egg-info/zip-safe
venv/lib/python3.6/site-packages/Werkzeug-0.12.2.dist-info/LICENSE.txt
venv/lib/python3.6/site-packages/Werkzeug-0.12.2.dist-info/top_level.txt
venv/lib/python3.6/site-packages/certifi-2017.7.27.1.dist-info/top_level.txt
venv/lib/python3.6/site-packages/chardet-3.0.4.dist-info/entry_points.txt
venv/lib/python3.6/site-packages/chardet-3.0.4.dist-info/top_level.txt
venv/lib/python3.6/site-packages/idna-2.6.dist-info/top_level.txt
venv/lib/python3.6/site-packages/lxml-4.0.0.dist-info/top_level.txt
venv/lib/python3.6/site-packages/lxml/isoschematron/resources/xsl/iso-schematron-xslt1/readme.txt
venv/lib/python3.6/site-packages/pip-9.0.1.dist-info/entry_points.txt
venv/lib/python3.6/site-packages/pip-9.0.1.dist-info/top_level.txt
venv/lib/python3.6/site-packages/python_dateutil-2.6.1.dist-info/top_level.txt
venv/lib/python3.6/site-packages/requests-2.18.4.dist-info/top_level.txt
venv/lib/python3.6/site-packages/setuptools-36.2.0.dist-info/dependency_links.txt
venv/lib/python3.6/site-packages/setuptools-36.2.0.dist-info/entry_points.txt
venv/lib/python3.6/site-packages/setuptools-36.2.0.dist-info/top_level.txt
venv/lib/python3.6/site-packages/six-1.11.0.dist-info/top_level.txt
venv/lib/python3.6/site-packages/urllib3-1.22.dist-info/top_level.txt
venv/lib64/python3.6/site-packages/Werkzeug-0.12.2.dist-info/LICENSE.txt
venv/lib64/python3.6/site-packages/Werkzeug-0.12.2.dist-info/top_level.txt
venv/lib64/python3.6/site-packages/certifi-2017.7.27.1.dist-info/top_level.txt
venv/lib64/python3.6/site-packages/chardet-3.0.4.dist-info/entry_points.txt
venv/lib64/python3.6/site-packages/chardet-3.0.4.dist-info/top_level.txt
venv/lib64/python3.6/site-packages/idna-2.6.dist-info/top_level.txt
venv/lib64/python3.6/site-packages/lxml-4.0.0.dist-info/top_level.txt
venv/lib64/python3.6/site-packages/lxml/isoschematron/resources/xsl/iso-schematron-xslt1/readme.txt
venv/lib64/python3.6/site-packages/pip-9.0.1.dist-info/entry_points.txt
venv/lib64/python3.6/site-packages/pip-9.0.1.dist-info/top_level.txt
venv/lib64/python3.6/site-packages/python_dateutil-2.6.1.dist-info/top_level.txt
venv/lib64/python3.6/site-packages/requests-2.18.4.dist-info/top_level.txt
venv/lib64/python3.6/site-packages/setuptools-36.2.0.dist-info/dependency_links.txt
venv/lib64/python3.6/site-packages/setuptools-36.2.0.dist-info/entry_points.txt
venv/lib64/python3.6/site-packages/setuptools-36.2.0.dist-info/top_level.txt
venv/lib64/python3.6/site-packages/six-1.11.0.dist-info/top_level.txt
venv/lib64/python3.6/site-packages/urllib3-1.22.dist-info/top_level.txt