Metadata-Version: 1.1
Name: crypto-price-rss
Version: 1.0.0
Summary: Ingest crypto prices and generate rss/atom file
Home-page: https://github.com/narfman0/crypto-price-rss
Author: Jon Robison
Author-email: narfman0@gmail.com
License: LICENSE
Keywords: crypto atom rss
Platform: UNKNOWN
Classifier: Development Status :: 4 - Beta
Classifier: License :: OSI Approved :: GNU General Public License v3 (GPLv3)
Classifier: Operating System :: OS Independent
Classifier: Programming Language :: Python
Classifier: Topic :: Software Development :: Libraries :: Python Modules
